simple_dvc/__init__.py
simple_dvc/__main__.py
simple_dvc/__main__.pyi
simple_dvc/api.py
simple_dvc/api.pyi
simple_dvc/cache_surgery.py
simple_dvc/cache_surgery.pyi
simple_dvc/cache_validate.py
simple_dvc/cache_validate.pyi
simple_dvc/demo.py
simple_dvc/demo.pyi
simple_dvc/discover_ssh_remote.py
simple_dvc/discover_ssh_remote.pyi
simple_dvc/main.py
simple_dvc/main.pyi
simple_dvc/py.typed
simple_dvc/registery.py
simple_dvc/registery.pyi
simple_dvc/sidecar.py
simple_dvc/util_fsspec.py
simple_dvc-0.2.1.dist-info/METADATA
simple_dvc-0.2.1.dist-info/WHEEL
simple_dvc-0.2.1.dist-info/entry_points.txt
simple_dvc-0.2.1.dist-info/top_level.txt
simple_dvc-0.2.1.dist-info/RECORD
