Metadata-Version: 2.1
Name: simple_dvc
Version: 0.2.1
Summary: The simple_dvc module
Home-page: https://gitlab.kitware.com/computer-vision/simple_dvc
Author: Jon Crall
Author-email: jon.crall@kitware.com
License: Apache 2
Classifier: Development Status :: 1 - Planning
Classifier: Intended Audience :: Developers
Classifier: Topic :: Software Development :: Libraries :: Python Modules
Classifier: Topic :: Utilities
Classifier: License :: OSI Approved :: Apache Software License
Classifier: Programming Language :: Python :: 3.8
Classifier: Programming Language :: Python :: 3.9
Classifier: Programming Language :: Python :: 3.10
Classifier: Programming Language :: Python :: 3.11
Classifier: Programming Language :: Python :: 3.12
Requires-Python: >=3.8
Requires-Dist: packaging >=21.3
Requires-Dist: ruamel.yaml >=0.17.22
Requires-Dist: kwutil >=0.2.3
Requires-Dist: argcomplete >=1.0
Requires-Dist: cmd-queue >=0.1.18
Requires-Dist: dvc >=3.7.0
Requires-Dist: pandas >=1.4.0 ; python_version < "3.10" and python_version >= "3.9"
Requires-Dist: pandas >=1.3.5 ; python_version < "3.11" and python_version >= "3.10"
Requires-Dist: PyYAML >=6.0 ; python_version < "3.12"
Requires-Dist: pandas >=1.5.0 ; python_version < "3.12" and python_version >= "3.11"
Requires-Dist: pandas >=1.0.0 ; python_version < "3.7" and python_version >= "3.6"
Requires-Dist: rich >=11.2.0 ; python_version < "3.8" and python_version >= "3.6"
Requires-Dist: pandas >=1.2.0 ; python_version < "3.8" and python_version >= "3.7"
Requires-Dist: pandas >=1.4.0 ; python_version < "3.9" and python_version >= "3.8"
Requires-Dist: PyYAML >=6.0.1 ; python_version < "4.0" and python_version >= "3.12"
Requires-Dist: pandas >=2.1.1 ; python_version < "4.0" and python_version >= "3.12"
Requires-Dist: ubelt >=1.3.3 ; python_version >= "3.6"
Requires-Dist: scriptconfig >=0.7.9 ; python_version >= "3.6"
Requires-Dist: rich >=12.4.4 ; python_version >= "3.8"
Provides-Extra: all
Requires-Dist: packaging >=21.3 ; extra == 'all'
Requires-Dist: ruamel.yaml >=0.17.22 ; extra == 'all'
Requires-Dist: kwutil >=0.2.3 ; extra == 'all'
Requires-Dist: argcomplete >=1.0 ; extra == 'all'
Requires-Dist: cmd-queue >=0.1.18 ; extra == 'all'
Requires-Dist: dvc >=3.7.0 ; extra == 'all'
Requires-Dist: xdoctest >=1.1.3 ; extra == 'all'
Requires-Dist: pytest-timeout >=1.4.2 ; extra == 'all'
Provides-Extra: all-strict
Requires-Dist: packaging ==21.3 ; extra == 'all-strict'
Requires-Dist: ruamel.yaml ==0.17.22 ; extra == 'all-strict'
Requires-Dist: kwutil ==0.2.3 ; extra == 'all-strict'
Requires-Dist: argcomplete ==1.0 ; extra == 'all-strict'
Requires-Dist: cmd-queue ==0.1.18 ; extra == 'all-strict'
Requires-Dist: dvc ==3.7.0 ; extra == 'all-strict'
Requires-Dist: xdoctest ==1.1.3 ; extra == 'all-strict'
Requires-Dist: pytest-timeout ==1.4.2 ; extra == 'all-strict'
Requires-Dist: coverage ==4.5 ; (python_version < "2.7" and python_version >= "2.6") and extra == 'all-strict'
Requires-Dist: pytest-cov ==2.8.1 ; (python_version < "2.8.0" and python_version >= "2.7.0") and extra == 'all-strict'
Requires-Dist: pandas ==1.4.0 ; (python_version < "3.10" and python_version >= "3.9") and extra == 'all-strict'
Requires-Dist: coverage ==5.3.1 ; (python_version < "3.10" and python_version >= "3.9") and extra == 'all-strict'
Requires-Dist: pytest ==6.2.5 ; (python_version < "3.10.0" and python_version >= "3.7.0") and extra == 'all-strict'
Requires-Dist: pandas ==1.3.5 ; (python_version < "3.11" and python_version >= "3.10") and extra == 'all-strict'
Requires-Dist: PyYAML ==6.0 ; (python_version < "3.12") and extra == 'all-strict'
Requires-Dist: pandas ==1.5.0 ; (python_version < "3.12" and python_version >= "3.11") and extra == 'all-strict'
Requires-Dist: coverage ==5.3.1 ; (python_version < "3.4" and python_version >= "2.7") and extra == 'all-strict'
Requires-Dist: coverage ==4.3.4 ; (python_version < "3.5" and python_version >= "3.4") and extra == 'all-strict'
Requires-Dist: pytest-cov ==2.8.1 ; (python_version < "3.5.0" and python_version >= "3.4.0") and extra == 'all-strict'
Requires-Dist: coverage ==5.3.1 ; (python_version < "3.6" and python_version >= "3.5") and extra == 'all-strict'
Requires-Dist: pytest-cov ==2.9.0 ; (python_version < "3.6.0" and python_version >= "3.5.0") and extra == 'all-strict'
Requires-Dist: pandas ==1.0.0 ; (python_version < "3.7" and python_version >= "3.6") and extra == 'all-strict'
Requires-Dist: coverage ==6.1.1 ; (python_version < "3.7" and python_version >= "3.6") and extra == 'all-strict'
Requires-Dist: pytest ==6.2.5 ; (python_version < "3.7.0" and python_version >= "3.6.0") and extra == 'all-strict'
Requires-Dist: rich ==11.2.0 ; (python_version < "3.8" and python_version >= "3.6") and extra == 'all-strict'
Requires-Dist: pandas ==1.2.0 ; (python_version < "3.8" and python_version >= "3.7") and extra == 'all-strict'
Requires-Dist: coverage ==6.1.1 ; (python_version < "3.8" and python_version >= "3.7") and extra == 'all-strict'
Requires-Dist: pandas ==1.4.0 ; (python_version < "3.9" and python_version >= "3.8") and extra == 'all-strict'
Requires-Dist: coverage ==6.1.1 ; (python_version < "3.9" and python_version >= "3.8") and extra == 'all-strict'
Requires-Dist: PyYAML ==6.0.1 ; (python_version < "4.0" and python_version >= "3.12") and extra == 'all-strict'
Requires-Dist: pandas ==2.1.1 ; (python_version < "4.0" and python_version >= "3.12") and extra == 'all-strict'
Requires-Dist: coverage ==6.1.1 ; (python_version >= "3.10") and extra == 'all-strict'
Requires-Dist: pytest ==6.2.5 ; (python_version >= "3.10.0") and extra == 'all-strict'
Requires-Dist: ubelt ==1.3.3 ; (python_version >= "3.6") and extra == 'all-strict'
Requires-Dist: scriptconfig ==0.7.9 ; (python_version >= "3.6") and extra == 'all-strict'
Requires-Dist: pytest-cov ==3.0.0 ; (python_version >= "3.6.0") and extra == 'all-strict'
Requires-Dist: rich ==12.4.4 ; (python_version >= "3.8") and extra == 'all-strict'
Requires-Dist: coverage >=4.5 ; (python_version < "2.7" and python_version >= "2.6") and extra == 'all'
Requires-Dist: pytest-cov >=2.8.1 ; (python_version < "2.8.0" and python_version >= "2.7.0") and extra == 'all'
Requires-Dist: pandas >=1.4.0 ; (python_version < "3.10" and python_version >= "3.9") and extra == 'all'
Requires-Dist: coverage >=5.3.1 ; (python_version < "3.10" and python_version >= "3.9") and extra == 'all'
Requires-Dist: pytest >=6.2.5 ; (python_version < "3.10.0" and python_version >= "3.7.0") and extra == 'all'
Requires-Dist: pandas >=1.3.5 ; (python_version < "3.11" and python_version >= "3.10") and extra == 'all'
Requires-Dist: PyYAML >=6.0 ; (python_version < "3.12") and extra == 'all'
Requires-Dist: pandas >=1.5.0 ; (python_version < "3.12" and python_version >= "3.11") and extra == 'all'
Requires-Dist: coverage >=5.3.1 ; (python_version < "3.4" and python_version >= "2.7") and extra == 'all'
Requires-Dist: coverage >=4.3.4 ; (python_version < "3.5" and python_version >= "3.4") and extra == 'all'
Requires-Dist: pytest-cov >=2.8.1 ; (python_version < "3.5.0" and python_version >= "3.4.0") and extra == 'all'
Requires-Dist: coverage >=5.3.1 ; (python_version < "3.6" and python_version >= "3.5") and extra == 'all'
Requires-Dist: pytest-cov >=2.9.0 ; (python_version < "3.6.0" and python_version >= "3.5.0") and extra == 'all'
Requires-Dist: pandas >=1.0.0 ; (python_version < "3.7" and python_version >= "3.6") and extra == 'all'
Requires-Dist: coverage >=6.1.1 ; (python_version < "3.7" and python_version >= "3.6") and extra == 'all'
Requires-Dist: pytest >=6.2.5 ; (python_version < "3.7.0" and python_version >= "3.6.0") and extra == 'all'
Requires-Dist: rich >=11.2.0 ; (python_version < "3.8" and python_version >= "3.6") and extra == 'all'
Requires-Dist: pandas >=1.2.0 ; (python_version < "3.8" and python_version >= "3.7") and extra == 'all'
Requires-Dist: coverage >=6.1.1 ; (python_version < "3.8" and python_version >= "3.7") and extra == 'all'
Requires-Dist: pandas >=1.4.0 ; (python_version < "3.9" and python_version >= "3.8") and extra == 'all'
Requires-Dist: coverage >=6.1.1 ; (python_version < "3.9" and python_version >= "3.8") and extra == 'all'
Requires-Dist: PyYAML >=6.0.1 ; (python_version < "4.0" and python_version >= "3.12") and extra == 'all'
Requires-Dist: pandas >=2.1.1 ; (python_version < "4.0" and python_version >= "3.12") and extra == 'all'
Requires-Dist: coverage >=6.1.1 ; (python_version >= "3.10") and extra == 'all'
Requires-Dist: pytest >=6.2.5 ; (python_version >= "3.10.0") and extra == 'all'
Requires-Dist: ubelt >=1.3.3 ; (python_version >= "3.6") and extra == 'all'
Requires-Dist: scriptconfig >=0.7.9 ; (python_version >= "3.6") and extra == 'all'
Requires-Dist: pytest-cov >=3.0.0 ; (python_version >= "3.6.0") and extra == 'all'
Requires-Dist: rich >=12.4.4 ; (python_version >= "3.8") and extra == 'all'
Provides-Extra: docs
Requires-Dist: sphinx >=5.0.1 ; extra == 'docs'
Requires-Dist: sphinx-autobuild >=2021.3.14 ; extra == 'docs'
Requires-Dist: sphinx-rtd-theme >=1.0.0 ; extra == 'docs'
Requires-Dist: sphinxcontrib-napoleon >=0.7 ; extra == 'docs'
Requires-Dist: sphinx-autoapi >=1.8.4 ; extra == 'docs'
Requires-Dist: Pygments >=2.9.0 ; extra == 'docs'
Requires-Dist: myst-parser >=0.18.0 ; extra == 'docs'
Requires-Dist: sphinx-reredirects >=0.0.1 ; extra == 'docs'
Provides-Extra: docs-strict
Requires-Dist: sphinx ==5.0.1 ; extra == 'docs-strict'
Requires-Dist: sphinx-autobuild ==2021.3.14 ; extra == 'docs-strict'
Requires-Dist: sphinx-rtd-theme ==1.0.0 ; extra == 'docs-strict'
Requires-Dist: sphinxcontrib-napoleon ==0.7 ; extra == 'docs-strict'
Requires-Dist: sphinx-autoapi ==1.8.4 ; extra == 'docs-strict'
Requires-Dist: Pygments ==2.9.0 ; extra == 'docs-strict'
Requires-Dist: myst-parser ==0.18.0 ; extra == 'docs-strict'
Requires-Dist: sphinx-reredirects ==0.0.1 ; extra == 'docs-strict'
Provides-Extra: linting
Requires-Dist: flake8 >=5.0.0 ; extra == 'linting'
Provides-Extra: linting-strict
Requires-Dist: flake8 ==5.0.0 ; extra == 'linting-strict'
Provides-Extra: optional
Provides-Extra: optional-strict
Provides-Extra: runtime
Requires-Dist: packaging >=21.3 ; extra == 'runtime'
Requires-Dist: ruamel.yaml >=0.17.22 ; extra == 'runtime'
Requires-Dist: kwutil >=0.2.3 ; extra == 'runtime'
Requires-Dist: argcomplete >=1.0 ; extra == 'runtime'
Requires-Dist: cmd-queue >=0.1.18 ; extra == 'runtime'
Requires-Dist: dvc >=3.7.0 ; extra == 'runtime'
Provides-Extra: runtime-strict
Requires-Dist: packaging ==21.3 ; extra == 'runtime-strict'
Requires-Dist: ruamel.yaml ==0.17.22 ; extra == 'runtime-strict'
Requires-Dist: kwutil ==0.2.3 ; extra == 'runtime-strict'
Requires-Dist: argcomplete ==1.0 ; extra == 'runtime-strict'
Requires-Dist: cmd-queue ==0.1.18 ; extra == 'runtime-strict'
Requires-Dist: dvc ==3.7.0 ; extra == 'runtime-strict'
Requires-Dist: pandas ==1.4.0 ; (python_version < "3.10" and python_version >= "3.9") and extra == 'runtime-strict'
Requires-Dist: pandas ==1.3.5 ; (python_version < "3.11" and python_version >= "3.10") and extra == 'runtime-strict'
Requires-Dist: PyYAML ==6.0 ; (python_version < "3.12") and extra == 'runtime-strict'
Requires-Dist: pandas ==1.5.0 ; (python_version < "3.12" and python_version >= "3.11") and extra == 'runtime-strict'
Requires-Dist: pandas ==1.0.0 ; (python_version < "3.7" and python_version >= "3.6") and extra == 'runtime-strict'
Requires-Dist: rich ==11.2.0 ; (python_version < "3.8" and python_version >= "3.6") and extra == 'runtime-strict'
Requires-Dist: pandas ==1.2.0 ; (python_version < "3.8" and python_version >= "3.7") and extra == 'runtime-strict'
Requires-Dist: pandas ==1.4.0 ; (python_version < "3.9" and python_version >= "3.8") and extra == 'runtime-strict'
Requires-Dist: PyYAML ==6.0.1 ; (python_version < "4.0" and python_version >= "3.12") and extra == 'runtime-strict'
Requires-Dist: pandas ==2.1.1 ; (python_version < "4.0" and python_version >= "3.12") and extra == 'runtime-strict'
Requires-Dist: ubelt ==1.3.3 ; (python_version >= "3.6") and extra == 'runtime-strict'
Requires-Dist: scriptconfig ==0.7.9 ; (python_version >= "3.6") and extra == 'runtime-strict'
Requires-Dist: rich ==12.4.4 ; (python_version >= "3.8") and extra == 'runtime-strict'
Requires-Dist: pandas >=1.4.0 ; (python_version < "3.10" and python_version >= "3.9") and extra == 'runtime'
Requires-Dist: pandas >=1.3.5 ; (python_version < "3.11" and python_version >= "3.10") and extra == 'runtime'
Requires-Dist: PyYAML >=6.0 ; (python_version < "3.12") and extra == 'runtime'
Requires-Dist: pandas >=1.5.0 ; (python_version < "3.12" and python_version >= "3.11") and extra == 'runtime'
Requires-Dist: pandas >=1.0.0 ; (python_version < "3.7" and python_version >= "3.6") and extra == 'runtime'
Requires-Dist: rich >=11.2.0 ; (python_version < "3.8" and python_version >= "3.6") and extra == 'runtime'
Requires-Dist: pandas >=1.2.0 ; (python_version < "3.8" and python_version >= "3.7") and extra == 'runtime'
Requires-Dist: pandas >=1.4.0 ; (python_version < "3.9" and python_version >= "3.8") and extra == 'runtime'
Requires-Dist: PyYAML >=6.0.1 ; (python_version < "4.0" and python_version >= "3.12") and extra == 'runtime'
Requires-Dist: pandas >=2.1.1 ; (python_version < "4.0" and python_version >= "3.12") and extra == 'runtime'
Requires-Dist: ubelt >=1.3.3 ; (python_version >= "3.6") and extra == 'runtime'
Requires-Dist: scriptconfig >=0.7.9 ; (python_version >= "3.6") and extra == 'runtime'
Requires-Dist: rich >=12.4.4 ; (python_version >= "3.8") and extra == 'runtime'
Provides-Extra: tests
Requires-Dist: xdoctest >=1.1.3 ; extra == 'tests'
Requires-Dist: pytest-timeout >=1.4.2 ; extra == 'tests'
Provides-Extra: tests-strict
Requires-Dist: xdoctest ==1.1.3 ; extra == 'tests-strict'
Requires-Dist: pytest-timeout ==1.4.2 ; extra == 'tests-strict'
Requires-Dist: coverage ==4.5 ; (python_version < "2.7" and python_version >= "2.6") and extra == 'tests-strict'
Requires-Dist: pytest-cov ==2.8.1 ; (python_version < "2.8.0" and python_version >= "2.7.0") and extra == 'tests-strict'
Requires-Dist: coverage ==5.3.1 ; (python_version < "3.10" and python_version >= "3.9") and extra == 'tests-strict'
Requires-Dist: pytest ==6.2.5 ; (python_version < "3.10.0" and python_version >= "3.7.0") and extra == 'tests-strict'
Requires-Dist: coverage ==5.3.1 ; (python_version < "3.4" and python_version >= "2.7") and extra == 'tests-strict'
Requires-Dist: coverage ==4.3.4 ; (python_version < "3.5" and python_version >= "3.4") and extra == 'tests-strict'
Requires-Dist: pytest-cov ==2.8.1 ; (python_version < "3.5.0" and python_version >= "3.4.0") and extra == 'tests-strict'
Requires-Dist: coverage ==5.3.1 ; (python_version < "3.6" and python_version >= "3.5") and extra == 'tests-strict'
Requires-Dist: pytest-cov ==2.9.0 ; (python_version < "3.6.0" and python_version >= "3.5.0") and extra == 'tests-strict'
Requires-Dist: coverage ==6.1.1 ; (python_version < "3.7" and python_version >= "3.6") and extra == 'tests-strict'
Requires-Dist: pytest ==6.2.5 ; (python_version < "3.7.0" and python_version >= "3.6.0") and extra == 'tests-strict'
Requires-Dist: coverage ==6.1.1 ; (python_version < "3.8" and python_version >= "3.7") and extra == 'tests-strict'
Requires-Dist: coverage ==6.1.1 ; (python_version < "3.9" and python_version >= "3.8") and extra == 'tests-strict'
Requires-Dist: coverage ==6.1.1 ; (python_version >= "3.10") and extra == 'tests-strict'
Requires-Dist: pytest ==6.2.5 ; (python_version >= "3.10.0") and extra == 'tests-strict'
Requires-Dist: pytest-cov ==3.0.0 ; (python_version >= "3.6.0") and extra == 'tests-strict'
Requires-Dist: coverage >=4.5 ; (python_version < "2.7" and python_version >= "2.6") and extra == 'tests'
Requires-Dist: pytest-cov >=2.8.1 ; (python_version < "2.8.0" and python_version >= "2.7.0") and extra == 'tests'
Requires-Dist: coverage >=5.3.1 ; (python_version < "3.10" and python_version >= "3.9") and extra == 'tests'
Requires-Dist: pytest >=6.2.5 ; (python_version < "3.10.0" and python_version >= "3.7.0") and extra == 'tests'
Requires-Dist: coverage >=5.3.1 ; (python_version < "3.4" and python_version >= "2.7") and extra == 'tests'
Requires-Dist: coverage >=4.3.4 ; (python_version < "3.5" and python_version >= "3.4") and extra == 'tests'
Requires-Dist: pytest-cov >=2.8.1 ; (python_version < "3.5.0" and python_version >= "3.4.0") and extra == 'tests'
Requires-Dist: coverage >=5.3.1 ; (python_version < "3.6" and python_version >= "3.5") and extra == 'tests'
Requires-Dist: pytest-cov >=2.9.0 ; (python_version < "3.6.0" and python_version >= "3.5.0") and extra == 'tests'
Requires-Dist: coverage >=6.1.1 ; (python_version < "3.7" and python_version >= "3.6") and extra == 'tests'
Requires-Dist: pytest >=6.2.5 ; (python_version < "3.7.0" and python_version >= "3.6.0") and extra == 'tests'
Requires-Dist: coverage >=6.1.1 ; (python_version < "3.8" and python_version >= "3.7") and extra == 'tests'
Requires-Dist: coverage >=6.1.1 ; (python_version < "3.9" and python_version >= "3.8") and extra == 'tests'
Requires-Dist: coverage >=6.1.1 ; (python_version >= "3.10") and extra == 'tests'
Requires-Dist: pytest >=6.2.5 ; (python_version >= "3.10.0") and extra == 'tests'
Requires-Dist: pytest-cov >=3.0.0 ; (python_version >= "3.6.0") and extra == 'tests'
